setup.py
gaussian_distribution/Binomialdistribution.py
gaussian_distribution/Gaussiandistribution.py
gaussian_distribution/Generaldistribution.py
gaussian_distribution/__init__.py
gaussian_distribution.egg-info/PKG-INFO
gaussian_distribution.egg-info/SOURCES.txt
gaussian_distribution.egg-info/dependency_links.txt
gaussian_distribution.egg-info/not-zip-safe
gaussian_distribution.egg-info/top_level.txt