Metadata-Version: 1.0
Name: gaussian-distribution
Version: 1.0
Summary: Gaussian and Binomnal distribution
Home-page: UNKNOWN
Author: Tim Krebs
Author-email: timkrebs9@gmail.com
License: UNKNOWN
Platform: UNKNOWN
